qantio/__init__.py
qantio/__pycache__/__init__.cpython-37.pyc
qantio/sdk/__init__.py
qantio/sdk/__pycache__/__init__.cpython-37.pyc
qantio/sdk/public/__init__.py
qantio/sdk/public/test.py
qantio/sdk/public/__pycache__/__init__.cpython-37.pyc
qantio/sdk/public/api/__init__.py
qantio/sdk/public/api/experiment.py
qantio/sdk/public/api/experiment_manager.py
qantio/sdk/public/api/ingestion.py
qantio/sdk/public/client/__init__.py
qantio/sdk/public/client/qantio_client.py
qantio/sdk/public/common/__init__.py
qantio/sdk/public/common/log.py
qantio/sdk/public/common/settings.py
qantio/sdk/public/common/__pycache__/__init__.cpython-37.pyc
qantio/sdk/public/common/__pycache__/log.cpython-37.pyc
qantio/sdk/public/common/__pycache__/settings.cpython-37.pyc
qantio/sdk/public/connectors/__init__.py
qantio/sdk/public/connectors/aws_s3.py
qantio/sdk/public/connectors/azure_blob.py
qantio/sdk/public/connectors/csv.py
qantio/sdk/public/connectors/ftp.py
qantio/sdk/public/connectors/pandas_loader.py
qantio/sdk/public/connectors/sql.py
qantio/sdk/public/core/__init__.py
qantio/sdk/public/exceptions/GeographyPointException.py
qantio/sdk/public/exceptions/__init__.py
qantio/sdk/public/helpers/__init__.py
qantio/sdk/public/helpers/pandas_readers.py
qantio/sdk/public/helpers/user_context.py
qantio/sdk/public/helpers/__pycache__/__init__.cpython-37.pyc
qantio/sdk/public/helpers/__pycache__/user_context.cpython-37.pyc
qantio/sdk/public/loaders/__init__.py
qantio/sdk/public/loaders/aws_s3_loader.py
qantio/sdk/public/loaders/az_blob_loader.py
qantio/sdk/public/loaders/csv_loader.py
qantio/sdk/public/loaders/ftp_loader.py
qantio/sdk/public/loaders/pandas_loader.py
qantio/sdk/public/loaders/sql_loader.py
qantio/sdk/public/logs/__init__.py
qantio/sdk/public/models/__init__.py
qantio/sdk/public/models/batch_operation_result.py
qantio/sdk/public/models/dataconnector.py
qantio/sdk/public/models/datapoint.py
qantio/sdk/public/models/datasource.py
qantio/sdk/public/models/experiment.py
Qantio.Sdk.Public-0.3.2.dist-info/METADATA
Qantio.Sdk.Public-0.3.2.dist-info/WHEEL
Qantio.Sdk.Public-0.3.2.dist-info/top_level.txt
Qantio.Sdk.Public-0.3.2.dist-info/RECORD
