Metadata-Version: 2.1
Name: Qantio.Sdk.Public
Version: 0.3.2
Summary: The official SDK to interract with qant.io time series analysis and prediction services.
Home-page: https://qant.io
Author: qant.io
Author-email: support@qant.io
License: MIT
Keywords: qant.io,qantio,time series,forecasting,analysis,prediction,autoML,prediction as a service.
Classifier: Environment :: Console
Classifier: Development Status :: 2 - Pre-Alpha
Classifier: Intended Audience :: Developers
Classifier: Operating System :: OS Independent
Classifier: License :: OSI Approved :: European Union Public Licence 1.2 (EUPL 1.2)
Classifier: Natural Language :: English
Classifier: Programming Language :: Python :: 3
Classifier: Programming Language :: Python :: 3.7
Classifier: Topic :: Software Development :: Libraries :: Python Modules
Classifier: Topic :: Scientific/Engineering :: Artificial Intelligence
Classifier: Topic :: Scientific/Engineering :: Information Analysis
Requires-Python: >=3.6
Requires-Dist: aiohttp
Requires-Dist: azure-storage-blob
Requires-Dist: boto3
Requires-Dist: colorlog
Requires-Dist: joblib
Requires-Dist: msal
Requires-Dist: opencensus
Requires-Dist: opencensus-ext-logging
Requires-Dist: opencensus-ext-azure
Requires-Dist: pandas
Requires-Dist: pandas-profiling
Requires-Dist: pyodbc
Requires-Dist: pyparsing
Requires-Dist: requests
Requires-Dist: requests-toolbelt
Requires-Dist: setuptools
Requires-Dist: python-slugify
Requires-Dist: urllib3
Requires-Dist: pyarrow
Requires-Dist: dataclasses-json
